{
  "categoria": "INOX",
  "produtos": [
    {
      "codigo": "4291",
      "descricao": "INOX BRINCO TRIO BORBOLETA PRETO TREVO E PONTO LUZ",
      "imagem": "4291.jpg",
      "pastaFotos": "Catalogos/Aco Inox/",
      "preco": "39,90",
      "precoConsignado": "59,90",
      "banho": "INOX",
      "dataUltimaEntrada": "22/04/2025"
    },
    {
      "codigo": "4290",
      "descricao": "INOX BRINCO TRIO BORBOLETA BRANCA TREVO E PONTO LUZ",
      "imagem": "4290.jpg",
      "pastaFotos": "Catalogos/Aco Inox/",
      "preco": "39,90",
      "precoConsignado": "59,90",
      "banho": "INOX",
      "dataUltimaEntrada": "22/04/2025"
    },
    {
      "codigo": "4289",
      "descricao": "INOX BRINCO TREVO MADREPEROLA M",
      "imagem": "4289.jpg",
      "pastaFotos": "Catalogos/Aco Inox/",
      "preco": "29,90",
      "precoConsignado": "42,90",
      "banho": "INOX",
      "dataUltimaEntrada": "22/04/2025"
    },
    {
      "codigo": "4288",
      "descricao": "INOX COLAR CONCHA CRAV. COM PEROLA INOX DOURADO 41+5CM",
      "imagem": "4288.jpg",
      "pastaFotos": "Catalogos/Aco Inox/",
      "preco": "49,90",
      "precoConsignado": "72,90",
      "banho": "INOX DOURADO",
      "dataUltimaEntrada": "19/04/2025"
    },
    {
      "codigo": "4287",
      "descricao": "INOX COLAR INFANTIL STITCH G RESINA INOX 47CM",
      "imagem": "4287.jpg",
      "pastaFotos": "Catalogos/Aco Inox/",
      "preco": "34,90",
      "precoConsignado": "52,90",
      "banho": "INOX",
      "dataUltimaEntrada": "19/04/2025"
    },
    {
      "codigo": "4286",
      "descricao": "INOX COLAR CORACOES COLORIDOS INOX 40+5CM",
      "imagem": "4286.jpg",
      "pastaFotos": "Catalogos/Aco Inox/",
      "preco": "39,90",
      "precoConsignado": "59,90",
      "banho": "INOX",
      "dataUltimaEntrada": "19/04/2025"
    },
    {
      "codigo": "4285",
      "descricao": "INOX COLAR INSP. PANTERA INOX DOURADO 44+8CM",
      "imagem": "4285.jpg",
      "pastaFotos": "Catalogos/Aco Inox/",
      "preco": "42,90",
      "precoConsignado": "64,90",
      "banho": "INOX DOURADO",
      "dataUltimaEntrada": "19/04/2025"
    },
    {
      "codigo": "4284",
      "descricao": "INOX COLAR Y 2 TREVOS E PONTO DE LUZ INOX 45+5CM",
      "imagem": "4284.jpg",
      "pastaFotos": "Catalogos/Aco Inox/",
      "preco": "49,90",
      "precoConsignado": "72,90",
      "banho": "INOX",
      "dataUltimaEntrada": "19/04/2025"
    },
    {
      "codigo": "4283",
      "descricao": "INOX COLAR TREVO E CIRCULO ENTRELACADOS INOX 46+5CM",
      "imagem": "4283.jpg",
      "pastaFotos": "Catalogos/Aco Inox/",
      "preco": "34,90",
      "precoConsignado": "54,90",
      "banho": "INOX",
      "dataUltimaEntrada": "19/04/2025"
    },
    {
      "codigo": "4282",
      "descricao": "INOX COLAR 5 FLORES INOX 47+5CM",
      "imagem": "4282.jpg",
      "pastaFotos": "Catalogos/Aco Inox/",
      "preco": "36,90",
      "precoConsignado": "59,90",
      "banho": "INOX",
      "dataUltimaEntrada": "19/04/2025"
    },
    {
      "codigo": "4281",
      "descricao": "INOX COLAR NOSSA SENHORA CRAVEJADA INOX 45+7CM",
      "imagem": "4281.jpg",
      "pastaFotos": "Catalogos/Aco Inox/",
      "preco": "36,90",
      "precoConsignado": "54,90",
      "banho": "INOX",
      "dataUltimaEntrada": "19/04/2025"
    },
    {
      "codigo": "4280",
      "descricao": "INOX COLAR CRUZ ZIRCONIAS CRISTAL INOX 43+7CM",
      "imagem": "4280.jpg",
      "pastaFotos": "Catalogos/Aco Inox/",
      "preco": "36,90",
      "precoConsignado": "59,90",
      "banho": "INOX",
      "dataUltimaEntrada": "19/04/2025"
    },
    {
      "codigo": "4279",
      "descricao": "INOX COLAR FADA CRAVEJADO INOX 45+7CM",
      "imagem": "4279.jpg",
      "pastaFotos": "Catalogos/Aco Inox/",
      "preco": "36,90",
      "precoConsignado": "59,90",
      "banho": "INOX",
      "dataUltimaEntrada": "19/04/2025"
    },
    {
      "codigo": "4278",
      "descricao": "INOX COLOAR 5 TREVOS PRETOS 44+5CM",
      "imagem": "4278.jpg",
      "pastaFotos": "Catalogos/Aco Inox/",
      "preco": "49,90",
      "precoConsignado": "79,90",
      "banho": "INOX",
      "dataUltimaEntrada": "19/04/2025"
    },
    {
      "codigo": "4277",
      "descricao": "INOX BRACELETE TREVO VERMELHO E PONTO DE LUZ",
      "imagem": "4277.jpg",
      "pastaFotos": "Catalogos/Aco Inox/",
      "preco": "42,90",
      "precoConsignado": "69,90",
      "banho": "INOX DOURADO",
      "dataUltimaEntrada": "18/04/2025"
    },
    {
      "codigo": "4276",
      "descricao": "INOX BRACELETE TREVO RESINA VERMELHO",
      "imagem": "4276.jpg",
      "pastaFotos": "Catalogos/Aco Inox/",
      "preco": "49,90",
      "precoConsignado": "74,90",
      "banho": "INOX DOURADO",
      "dataUltimaEntrada": "18/04/2025"
    },
    {
      "codigo": "4275",
      "descricao": "INOX BRACELETE 2 TREVOS E QUADRADOS BRANCO",
      "imagem": "4275.jpg",
      "pastaFotos": "Catalogos/Aco Inox/",
      "preco": "42,90",
      "precoConsignado": "74,90",
      "banho": "INOX DOURADO",
      "dataUltimaEntrada": "18/04/2025"
    },
    {
      "codigo": "4274",
      "descricao": "INOX BRACELETE 2 TREVOS E QUADRADOS VERMELHO",
      "imagem": "4274.jpg",
      "pastaFotos": "Catalogos/Aco Inox/",
      "preco": "42,90",
      "precoConsignado": "74,90",
      "banho": "INOX DOURADO",
      "dataUltimaEntrada": "18/04/2025"
    },
    {
      "codigo": "4273",
      "descricao": "INOX BRACELETE TREVO VERDE E 2 CRISTAIS",
      "imagem": "4273.jpg",
      "pastaFotos": "Catalogos/Aco Inox/",
      "preco": "42,90",
      "precoConsignado": "64,90",
      "banho": "INOX DOURADO",
      "dataUltimaEntrada": "18/04/2025"
    },
    {
      "codigo": "4272",
      "descricao": "INOX BRACELETE NO",
      "imagem": "4272.jpg",
      "pastaFotos": "Catalogos/Aco Inox/",
      "preco": "39,90",
      "precoConsignado": "62,90",
      "banho": "INOX",
      "dataUltimaEntrada": "18/04/2025"
    },
    {
      "codigo": "4260",
      "descricao": "INOX CONJUNTO TREVO CINZA PEROLADO 46CM",
      "imagem": "4260.jpg",
      "pastaFotos": "Catalogos/Aco Inox/",
      "preco": "49,90",
      "precoConsignado": "79,90",
      "banho": "INOX",
      "dataUltimaEntrada": "15/04/2025"
    },
    {
      "codigo": "4259",
      "descricao": "INOX CONJUNTO CORACAO LAVANDA 45CM",
      "imagem": "4259.jpg",
      "pastaFotos": "Catalogos/Aco Inox/",
      "preco": "32,90",
      "precoConsignado": "49,90",
      "banho": "INOX",
      "dataUltimaEntrada": "15/04/2025"
    },
    {
      "codigo": "4258",
      "descricao": "INOX CONJUNTO TREVO BRANCO ESMALTADO 51CM",
      "imagem": "4258.jpg",
      "pastaFotos": "Catalogos/Aco Inox/",
      "preco": "32,90",
      "precoConsignado": "49,90",
      "banho": "INOX",
      "dataUltimaEntrada": "15/04/2025"
    },
    {
      "codigo": "4254",
      "descricao": "INOX BRACELETE 5 TREVOS PRETOS",
      "imagem": "4254.jpg",
      "pastaFotos": "Catalogos/Aco Inox/",
      "preco": "42,90",
      "precoConsignado": "64,90",
      "banho": "INOX DOURADO",
      "dataUltimaEntrada": "14/04/2025"
    },
    {
      "codigo": "4253",
      "descricao": "INOX BRACELETE INSP CIRCULOS PRETOS COM PEDRAS",
      "imagem": "4253.jpg",
      "pastaFotos": "Catalogos/Aco Inox/",
      "preco": "42,90",
      "precoConsignado": "64,90",
      "banho": "INOX DOURADO",
      "dataUltimaEntrada": "14/04/2025"
    },
    {
      "codigo": "4252",
      "descricao": "INOX BRACELETE CIRCULO PRETO E ALGARISMOS INSP",
      "imagem": "4252.jpg",
      "pastaFotos": "Catalogos/Aco Inox/",
      "preco": "42,90",
      "precoConsignado": "69,90",
      "banho": "INOX",
      "dataUltimaEntrada": "14/04/2025"
    },
    {
      "codigo": "4251",
      "descricao": "INOX BRACELETE CORACAO PRETO E MADREPEROLA",
      "imagem": "4251.jpg",
      "pastaFotos": "Catalogos/Aco Inox/",
      "preco": "42,90",
      "precoConsignado": "69,90",
      "banho": "INOX DOURADO",
      "dataUltimaEntrada": "14/04/2025"
    },
    {
      "codigo": "4231",
      "descricao": "INOX ANEL TREVO PRETO INSP. - TAMANHOS",
      "imagem": "4231.jpg",
      "pastaFotos": "Catalogos/Aco Inox/",
      "preco": "22,90",
      "precoConsignado": "39,90",
      "banho": "INOX DOURADO",
      "dataUltimaEntrada": "12/04/2025"
    },
    {
      "codigo": "4230",
      "descricao": "INOX ANEL TREVO BRANCO INSP. - TAMANHOS",
      "imagem": "4230.jpg",
      "pastaFotos": "Catalogos/Aco Inox/",
      "preco": "22,90",
      "precoConsignado": "39,90",
      "banho": "INOX DOURADO",
      "dataUltimaEntrada": "12/04/2025"
    },
    {
      "codigo": "4222",
      "descricao": "INOX COLAR URSINHO CRAVEJADO INOX DOURADO 50CM",
      "imagem": "4222.jpg",
      "pastaFotos": "Catalogos/Aco Inox/",
      "preco": "49,90",
      "precoConsignado": "74,90",
      "banho": "INOX DOURADO",
      "dataUltimaEntrada": "11/04/2025"
    },
    {
      "codigo": "4216",
      "descricao": "INOX CONJUNTO INFANTIL HELLO KITTY 40CM",
      "imagem": "4216.jpg",
      "pastaFotos": "Catalogos/Aco Inox/",
      "preco": "39,90",
      "precoConsignado": "59,90",
      "banho": "INOX",
      "dataUltimaEntrada": "10/04/2025"
    },
    {
      "codigo": "4215",
      "descricao": "INOX CONJUNTO INFANTIL CEREJA 40CM",
      "imagem": "4215.jpg",
      "pastaFotos": "Catalogos/Aco Inox/",
      "preco": "34,90",
      "precoConsignado": "56,90",
      "banho": "INOX",
      "dataUltimaEntrada": "10/04/2025"
    },
    {
      "codigo": "4012",
      "descricao": "INOX PULSEIRA BERLOQUES FIXOS MAO",
      "imagem": "4012.jpg",
      "pastaFotos": "Catalogos/Aco Inox/",
      "preco": "34,90",
      "precoConsignado": "52,90",
      "banho": "INOX",
      "dataUltimaEntrada": "10/04/2025"
    },
    {
      "codigo": "4213",
      "descricao": "INOX PULSEIRA BERLOQUES FIXOS ARVORES DA VIDA",
      "imagem": "4213.jpg",
      "pastaFotos": "Catalogos/Aco Inox/",
      "preco": "34,90",
      "precoConsignado": "52,90",
      "banho": "INOX",
      "dataUltimaEntrada": "09/04/2025"
    },
    {
      "codigo": "4211",
      "descricao": "INOX BRINCO TREVO PRETO M",
      "imagem": "4211.jpg",
      "pastaFotos": "Catalogos/Aco Inox/",
      "preco": "29,90",
      "precoConsignado": "42,90",
      "banho": "INOX DOURADO",
      "dataUltimaEntrada": "09/04/2025"
    },
    {
      "codigo": "4208",
      "descricao": "INOX BRINCO TREVO MADREPEROLA P",
      "imagem": "4208.jpg",
      "pastaFotos": "Catalogos/Aco Inox/",
      "preco": "24,90",
      "precoConsignado": "39,90",
      "banho": "INOX DOURADO",
      "dataUltimaEntrada": "09/04/2025"
    },
    {
      "codigo": "4205",
      "descricao": "INOX PULSEIRA INSP. JOANINHA/TREVO/CORACAO",
      "imagem": "4205.jpg",
      "pastaFotos": "Catalogos/Aco Inox/",
      "preco": "46,90",
      "precoConsignado": "74,90",
      "banho": "INOX DOURADO",
      "dataUltimaEntrada": "08/04/2025"
    },
    {
      "codigo": "4204",
      "descricao": "INOX COLAR INSP. JOANINHA/TREVO/CORACAO 44+5CM",
      "imagem": "4204.jpg",
      "pastaFotos": "Catalogos/Aco Inox/",
      "preco": "49,90",
      "precoConsignado": "79,90",
      "banho": "INOX DOURADO",
      "dataUltimaEntrada": "08/04/2025"
    },
    {
      "codigo": "4044",
      "descricao": "INOX COLAR INSP. JOANINHA/TREVO/CORACAO 44+5CM",
      "imagem": "4044.jpg",
      "pastaFotos": "Catalogos/Aco Inox/",
      "preco": "49,90",
      "precoConsignado": "79,90",
      "banho": "INOX",
      "dataUltimaEntrada": "08/04/2025"
    },
    {
      "codigo": "4179",
      "descricao": "INOX BRINCO ARGOLA TRIPLA RETANGULAR",
      "imagem": "4179.jpg",
      "pastaFotos": "Catalogos/Aco Inox/",
      "preco": "32,90",
      "precoConsignado": "49,90",
      "banho": "INOX",
      "dataUltimaEntrada": "01/04/2025"
    },
    {
      "codigo": "4178",
      "descricao": "INOX BRINCO ARGOLA TRIPLA TUBULAR",
      "imagem": "4178.jpg",
      "pastaFotos": "Catalogos/Aco Inox/",
      "preco": "32,90",
      "precoConsignado": "49,90",
      "banho": "INOX",
      "dataUltimaEntrada": "01/04/2025"
    },
    {
      "codigo": "4176",
      "descricao": "INOX BRINCO TRIO ARGOLA LISA",
      "imagem": "4176.jpg",
      "pastaFotos": "Catalogos/Aco Inox/",
      "preco": "29,90",
      "precoConsignado": "49,90",
      "banho": "INOX",
      "dataUltimaEntrada": "01/04/2025"
    },
    {
      "codigo": "4171",
      "descricao": "INOX COLAR 2 CORACOES 41+5CM",
      "imagem": "4171.jpg",
      "pastaFotos": "Catalogos/Aco Inox/",
      "preco": "49,90",
      "precoConsignado": "79,90",
      "banho": "INOX",
      "dataUltimaEntrada": "01/04/2025"
    },
    {
      "codigo": "4170",
      "descricao": "INOX COLAR BORBOLETA RESINA PEROLADA 40+5CM",
      "imagem": "4170.jpg",
      "pastaFotos": "Catalogos/Aco Inox/",
      "preco": "49,90",
      "precoConsignado": "79,90",
      "banho": "INOX",
      "dataUltimaEntrada": "01/04/2025"
    },
    {
      "codigo": "4065",
      "descricao": "INOX COLAR DUPLO INSPIRACAO 38+5CM",
      "imagem": "4065.jpg",
      "pastaFotos": "Catalogos/Aco Inox/",
      "preco": "49,90",
      "precoConsignado": "79,90",
      "banho": "INOX",
      "dataUltimaEntrada": "20/02/2025"
    },
    {
      "codigo": "4058",
      "descricao": "INOX BRINCO OVAL ORGANICO",
      "imagem": "4058.jpg",
      "pastaFotos": "Catalogos/Aco Inox/",
      "preco": "32,90",
      "precoConsignado": "54,90",
      "banho": "INOX",
      "dataUltimaEntrada": "19/02/2025"
    },
    {
      "codigo": "4055",
      "descricao": "INOX BRINCO CORACAO RESINA BRANCA CRISTAIS",
      "imagem": "4055.jpg",
      "pastaFotos": "Catalogos/Aco Inox/",
      "preco": "24,90",
      "precoConsignado": "44,90",
      "banho": "INOX",
      "dataUltimaEntrada": "19/02/2025"
    },
    {
      "codigo": "3991",
      "descricao": "INOX BRACELETE INSPIRACAO COM PEDRAS",
      "imagem": "3991.jpg",
      "pastaFotos": "Catalogos/Aco Inox/",
      "preco": "42,90",
      "precoConsignado": "64,90",
      "banho": "INOX",
      "dataUltimaEntrada": "12/02/2025"
    },
    {
      "codigo": "3990",
      "descricao": "INOX BRACELETE BVLGARI PRETO E BRANCO COM PEDRAS",
      "imagem": "3990.jpg",
      "pastaFotos": "Catalogos/Aco Inox/",
      "preco": "42,90",
      "precoConsignado": "64,90",
      "banho": "INOX",
      "dataUltimaEntrada": "12/02/2025"
    }
  ]
}
